geoiojpg/__init__.py
geoiojpg/base.py
geoiojpg-0.2.dist-info/DESCRIPTION.rst
geoiojpg-0.2.dist-info/METADATA
geoiojpg-0.2.dist-info/RECORD
geoiojpg-0.2.dist-info/WHEEL
geoiojpg-0.2.dist-info/metadata.json
geoiojpg-0.2.dist-info/top_level.txt
