Metadata-Version: 2.0
Name: geoiojpg
Version: 0.2
Summary: A wrapper around GeoIO for non-georeferenced jpg files
Home-page: https://github.com/ArnholdInstitute/geoiojpg
Author: Matt Le
Author-email: lematt1991@gmail.com
License: UNKNOWN
Download-URL: https://github.com/ArnholdInstitute/geoiojpg/archive/master.zip
Keywords: jpg,jpeg,geoio,geospatial
Platform: UNKNOWN
Requires-Dist: geoio
Requires-Dist: shapely
